CHANGELOG.md
LICENSE.txt
wagtail_sb_admin_interface/__init__.py
wagtail_sb_admin_interface/admin.py
wagtail_sb_admin_interface/apps.py
wagtail_sb_admin_interface/cache.py
wagtail_sb_admin_interface/compat.py
wagtail_sb_admin_interface/migrations/0001_initial.py
wagtail_sb_admin_interface/migrations/0002_remove_theme_color_input_focus_and_more.py
wagtail_sb_admin_interface/migrations/0003_remove_theme_sidebar_logo_background_color.py
wagtail_sb_admin_interface/migrations/0004_alter_theme_color_critical_alter_theme_color_info_and_more.py
wagtail_sb_admin_interface/migrations/0005_rename_sidebar_logo_mobile_theme_sidebar_logo_collapsed.py
wagtail_sb_admin_interface/migrations/0006_theme_sidebar_logo_background_color.py
wagtail_sb_admin_interface/migrations/0007_alter_theme_active_alter_theme_color_critical_and_more.py
wagtail_sb_admin_interface/migrations/__init__.py
wagtail_sb_admin_interface/models.py
wagtail_sb_admin_interface/settings.py
wagtail_sb_admin_interface/templates/wagtail_sb_admin_interface/icons/paintbrush-solid.svg
wagtail_sb_admin_interface/templates/wagtailadmin/base.html
wagtail_sb_admin_interface/templatetags/__init__.py
wagtail_sb_admin_interface/templatetags/wagtail_sb_admin_interface_tags.py
wagtail_sb_admin_interface/tests.py
wagtail_sb_admin_interface/version.py
wagtail_sb_admin_interface/views.py
wagtail_sb_admin_interface/wagtail_hooks.py
wagtail_sb_admin_interface-0.7.0.dist-info/LICENSE.txt
wagtail_sb_admin_interface-0.7.0.dist-info/METADATA
wagtail_sb_admin_interface-0.7.0.dist-info/WHEEL
wagtail_sb_admin_interface-0.7.0.dist-info/RECORD
