Metadata-Version: 2.1
Name: wagtail-sb-admin-interface
Version: 0.7.0
Summary: Customize the Wagtail admin interface from the admin itself.
Home-page: https://gitlab.com/softbutterfly/open-source/wagtail-sb-admin-interface
License: MIT
Keywords: Softbutterfly,Django,Migrations
Author: SoftButterfly Development Team
Author-email: dev@softbutterfly.io
Requires-Python: >=3.9.0,<4.0.0
Classifier: Development Status :: 4 - Beta
Classifier: Environment :: Web Environment
Classifier: Intended Audience :: Developers
Classifier: License :: OSI Approved :: MIT License
Classifier: Natural Language :: English
Classifier: Programming Language :: Python :: 3
Classifier: Programming Language :: Python :: 3.9
Classifier: Programming Language :: Python :: 3.10
Classifier: Programming Language :: Python :: 3.11
Classifier: Programming Language :: Python :: 3.12
Classifier: Topic :: Software Development :: Libraries :: Python Modules
Requires-Dist: django (<5.0)
Requires-Dist: django-colorfield (<1.0.0)
Requires-Dist: wagtail (<6.0)
Project-URL: Bug Tracker, https://gitlab.com/softbutterfly/open-source/wagtail-sb-admin-interface/-/issues
Project-URL: Documentation, https://gitlab.com/softbutterfly/open-source/wagtail-sb-admin-interface/-/wikis
Project-URL: Download, https://gitlab.com/softbutterfly/open-source/wagtail-sb-admin-interface/-/archive/v0.7.0/wagtail-sb-admin-interface-v0.7.0.tar.gz
Project-URL: Repository, https://gitlab.com/softbutterfly/open-source/wagtail-sb-admin-interface
